[
  {
    "title": "Пирог «Искушение в раю»",
    "photo": "искушение_в_раю.webp",
    "time": "1 час 20 минут",
    "calories": 380,
    "ingredients": [
      { "id": "flour",          "name": "400 г муки",                  "essential": true,  "important": false },
      { "id": "butter",         "name": "120 г сливочного масла",      "essential": true,  "important": false },
      { "id": "cocoa",          "name": "50 г какао-порошка",          "essential": false, "important": true },
      { "id": "sugar",          "name": "80 г сахара",                 "essential": false, "important": true },
      { "id": "baking_powder",  "name": "2 ч. л. разрыхлителя",        "essential": false, "important": false },
      { "id": "cottage_cheese", "name": "400 г творога",               "essential": false, "important": true },
      { "id": "eggs",           "name": "4 яйца",                      "essential": false, "important": true },
      { "id": "starch",         "name": "2 ст. л. крахмала",           "essential": false, "important": false },
      { "id": "peaches",        "name": "4 персика",                   "essential": false, "important": false }
    ],
    "steps": [
      "Смешать муку с разрыхлителем",
      "Растопить масло, смешать с сахаром, какао-порошком и мукой. Тесто получается крошкообразным, как песок",
      "Для начинки смешать творог, творожная масса с изюмом, сахар, яйца, крахмал и ваниль",
      "Персики вымыть и нарезать дольками",
      "На дно формы выложить половину теста, сверху — часть начинки",
      "Уложить персики, выложить оставшуюся начинку и присыпать оставшимся тестом",
      "Выпекать при 200°C около 1 часа"
    ]
  },
  {
    "title": "Пончики на сгущёнке",
    "photo": "пончики_на_сгущенке.webp",
    "time": "35 минут",
    "calories": 280,
    "ingredients": [
      { "id": "flour",          "name": "150–175 г муки",              "essential": true,  "important": false },
      { "id": "condensed_milk", "name": "100 г сгущённого молока",     "essential": true,  "important": false },
      { "id": "eggs",           "name": "1 яйцо",                      "essential": false, "important": true },
      { "id": "baking_powder",  "name": "0,5 ч. л. разрыхлителя",      "essential": false, "important": false },
      { "id": "salt",           "name": "соль — 1 щепотка",            "essential": false, "important": false }
    ],
    "steps": [
      "Сгущённое молоко перелить в миску, добавить яйцо и соль, взбить до однородности",
      "Просеять муку с разрыхлителем прямо в смесь и замесить пластичное тесто",
      "Завернуть тесто в плёнку и дать отдохнуть 15 минут",
      "Обмять тесто на столе (без дополнительной муки), разделить на 3 части",
      "Скатать из частей тонкие колбаски и нарезать кусочками по 1,5-2 см",
      "Скатать из кусочков шарики (тесто не липнет к рукам)",
      "Разогреть масло в сотейнике и обжаривать пончики небольшими партиями на среднем огне до румяной корочки",
      "Готовые пончики выкладывать на салфетку для удаления излишков масла, затем посыпать сахарной пудрой"
    ]
  },
  {
    "title": "Классический чизкейк",
    "photo": "классический_чизкейк.webp",
    "time": "2 часа 30 минут",
    "calories": 450,
    "ingredients": [
      { "id": "biscuits",       "name": "200 г крекеров",              "essential": true,  "important": false },
      { "id": "butter",         "name": "100 г сливочного масла",      "essential": true,  "important": false },
      { "id": "cream_cheese",   "name": "1 кг сливочного сыра",        "essential": true,  "important": false },
      { "id": "eggs",           "name": "4 крупных яйца",              "essential": false, "important": true },
      { "id": "sugar",          "name": "1 стакан сахара",             "essential": false, "important": true },
      { "id": "sour_cream",     "name": "200–250 г жирной сметаны",    "essential": false, "important": false }
    ],
    "steps": [
      "Разогреть духовку до 180°C. Смазать маслом разъёмную форму",
      "Измельчить крекеры в блендере, добавить растопленное масло, сахар и соль, перемешать",
      "Выложить массу в форму, равномерно распределить по дну и краям, придавливая пальцами",
      "Выпекать основу при 150°C 12-15 минут, затем остудить на решётке",
      "Взбить сливочный сыр (комнатной температуры) миксером на средней скорости",
      "Постепенно добавить сахар, лимонную цедру, сок и соль",
      "Вбить яйца по одному, добавить сметану, взбить до однородности",
      "Завернуть низ формы в фольгу, вылить начинку на основу, слегка стукнуть формой о стол для удаления пузырьков воздуха",
      "Поставить форму в глубокий противень, налить кипяток до половины высоты формы (водяная баня)",
      "Выпекать: сначала при 200°C 10-15 минут, затем уменьшить температуру до 110-120°C и выпекать ещё около 1,5 часов",
      "Вынуть из воды, оставить в выключенной духовке на 20 минут, затем остудить при комнатной температуре",
      "Провести ножом по стенкам формы, убрать в холодильник на несколько часов (лучше на ночь), затем аккуратно снять бортик"
    ]
  },
  {
    "title": "Рафаэлло (быстрый способ)",
    "photo": "рафаэло.webp",
    "time": "1 час 20 минут",
    "calories": 220,
    "ingredients": [
      { "id": "corn_sticks",    "name": "60 г кукурузных палочек",     "essential": true,  "important": false },
      { "id": "condensed_milk", "name": "5–6 ст. л. сгущённого молока","essential": true,  "important": false },
      { "id": "butter",         "name": "½ ч. л. сливочного масла",    "essential": false, "important": true },
      { "id": "coconut",        "name": "100 г кокосовой стружки",     "essential": false, "important": true },
      { "id": "peanuts",        "name": "горсть арахиса",              "essential": false, "important": false }
    ],
    "steps": [
      "Перемолоть кукурузные палочки через мясорубку",
      "Добавить сгущёнку и размягчённое масло, перемешать до однородной массы",
      "Отправить тесто в холодильник на 1 час для скрепления",
      "Тем временем поджарить арахис, остудить и снять шелуху",
      "Достать тесто из холодильника. С помощью чайной ложки отщипнуть порцию, сформировать лепёшку",
      "Положить в центр арахис, защипнуть края и сформировать шарик",
      "Обвалять шарик в кокосовой стружке",
      "При наличии — разложить в формочки для конфет, отправить в холодильник",
      "Доставать за 5 минут до подачи"
    ]
  },
  {
    "title": "Творожные сырки в шоколаде с вареньем",
    "photo": "творожные_сырки.webp",
    "time": "1 час 30 минут",
    "calories": 320,
    "ingredients": [
      { "id": "chocolate",      "name": "180 г молочного шоколада",    "essential": true,  "important": false },
      { "id": "cottage_cheese", "name": "300 г творога",               "essential": true,  "important": false },
      { "id": "butter",         "name": "40 г сливочного масла",       "essential": false, "important": true },
      { "id": "sugar_powder",   "name": "3 ст. л. сахарной пудры",     "essential": false, "important": true },
      { "id": "jam",            "name": "варенье (яблочное или другое) — 6 ч. л.", "essential": false, "important": false }
    ],
    "steps": [
      "Соединить в блендере творог, сахарную пудру, соль, ванилин и мягкое сливочное масло",
      "Измельчить до получения гладкой творожной массы",
      "Растопить шоколад на водяной бане или в микроволновке импульсами по 10-15 секунд",
      "Смазать растопленным шоколадом дно и бортики силиконовых формочек",
      "Поставить формочки в морозилку на 5 минут до застывания первого слоя",
      "Нанести второй слой шоколада и снова отправить в морозилку на 5 минут",
      "Переложить творожную массу в кондитерский мешок",
      "Отсадить массу в шоколадные «гнёздышки», оставляя углубление для начинки",
      "В углубления выложить варенье",
      "Накрыть начинку оставшейся творожной массой и разровнять поверхность",
      "Покрыть сырки оставшимся шоколадом и поставить в холодильник на 40-60 минут",
      "Аккуратно извлечь сырки из формочек и подавать к горячему напитку"
    ]
  },
  {
    "title": "Вафельные трубочки с варёной сгущёнкой (на сковороде)",
    "photo": "вафельные_трубочки_сгущенка.webp",
    "time": "25 минут",
    "calories": 290,
    "ingredients": [
      { "id": "flour",          "name": "90 г муки",                   "essential": true,  "important": false },
      { "id": "eggs",           "name": "3 яйца",                      "essential": true,  "important": false },
      { "id": "butter",         "name": "100 г сливочного масла",      "essential": false, "important": true },
      { "id": "sugar",          "name": "100 г сахара",                "essential": false, "important": true },
      { "id": "condensed_milk", "name": "варёная сгущёнка — 12 ст. л.", "essential": false, "important": true }
    ],
    "steps": [
      "Взбить яйца с сахаром, солью и ванилином до пены",
      "Растопить сливочное масло, остудить и влить в яичную смесь, взбить",
      "Добавить муку, замесить жидкое блинное тесто",
      "Сковороду смазать маслом, прогреть, вылить 1–1,5 ст.л. теста, размазать в тонкую лепёшку",
      "Жарить 30–40 секунд с одной стороны, перевернуть и жарить до золотистости",
      "Горячую вафлю сразу смазать варёной сгущёнкой и свернуть в трубочку",
      "Повторить с остальным тестом (получится ~12 трубочек)",
      "Перед подачей посыпать сахарной пудрой"
    ]
  },
  {
    "title": "Лимонный пирог",
    "photo": "лимонный_пирог.webp",
    "time": "1 час 30 минут",
    "calories": 420,
    "ingredients": [
      { "id": "flour",          "name": "150 г муки",                  "essential": true,  "important": false },
      { "id": "butter",         "name": "120 г сливочного масла",      "essential": true,  "important": false },
      { "id": "sugar_powder",   "name": "½ стакана сахарной пудры",    "essential": false, "important": true },
      { "id": "cocoa",          "name": "¼ стакана какао-порошка",     "essential": false, "important": false },
      { "id": "eggs",           "name": "3 крупных яйца",              "essential": false, "important": true },
      { "id": "cream",          "name": "250 мл жирных сливок",        "essential": false, "important": true }
    ],
    "steps": [
      "Просеять муку с сахарной пудрой, какао и солью",
      "Добавить холодное масло кубиками, перетереть в крошку",
      "Влить ледяную воду, быстро замесить тесто, охладить 30 минут",
      "Раскатать тесто, выложить в форму ~24 см с бортиками",
      "Накрыть пергаментом, засыпать грузом, выпекать 15 минут при 200°C",
      "Убрать груз, взбить яйца с сахаром, добавить сливки, цедру и соки лимона/лайма",
      "Вылить начинку на основу, выпекать 30–35 минут при 170°C",
      "Остудить до комнатной температуры перед подачей"
    ]
  },
  {
    "title": "Рогалики из слоёного теста с вареньем",
    "photo": "рогалики_варенье.webp",
    "time": "40 минут",
    "calories": 180,
    "ingredients": [
      { "id": "puff_pastry",    "name": "450 г слоёного бездрожжевого теста", "essential": true,  "important": false },
      { "id": "jam",            "name": "160 г густого варенья",            "essential": true,  "important": false },
      { "id": "flour",          "name": "30 г пшеничной муки (для подпыления)","essential": false, "important": false },
      { "id": "milk",           "name": "20 мл молока",                     "essential": false, "important": false },
      { "id": "eggs",           "name": "1 яйцо",                           "essential": false, "important": true }
    ],
    "steps": [
      "Дать тесту немного согреться (не размораживать полностью)",
      "Раскатать тесто на подпыленной мукой поверхности толщиной 4–5 мм",
      "Разрезать на треугольники",
      "На широкую часть положить ~1 ч.л. варенья",
      "Свернуть рогалики от широкой стороны к острию",
      "Смешать желток с молоком, смазать рогалики",
      "Выпекать на пергаменте 15–17 минут при 180°C до золотистости",
      "Посыпать сахаром или пудрой после выпечки"
    ]
  },
  {
    "title": "Пирожное Вупи (американское)",
    "photo": "вупи_пирожное.webp",
    "time": "40 минут",
    "calories": 350,
    "ingredients": [
      { "id": "eggs",           "name": "1 яйцо",                      "essential": true,  "important": false },
      { "id": "butter",         "name": "80 г сливочного масла",       "essential": true,  "important": false },
      { "id": "flour",          "name": "130 г муки",                  "essential": false, "important": true },
      { "id": "cocoa",          "name": "3 ст. л. какао",              "essential": false, "important": true },
      { "id": "milk",           "name": "100 мл молока",               "essential": false, "important": false },
      { "id": "cream",          "name": "150 мл жирных сливок",        "essential": false, "important": true }
    ],
    "steps": [
      "Смешать сухие ингредиенты: муку, какао, разрыхлитель, ванилин",
      "Растереть масло с пудрой, вбить яйцо",
      "Частями добавить сухую смесь и молоко, замесить тесто",
      "Выложить круглые лепёшки на противень",
      "Выпекать 10–12 минут при 180°C, остудить",
      "Взбить сливки с пудрой до пиков",
      "Нанести крем на одну половинку, накрыть вторую",
      "По желанию посыпать пудрой"
    ]
  },
  {
    "title": "Медовое печенье с корицей",
    "photo": "медовое_печенье_корица.webp",
    "time": "25 минут",
    "calories": 210,
    "ingredients": [
      { "id": "eggs",           "name": "2 яйца",                      "essential": true,  "important": false },
      { "id": "sugar",          "name": "130 г сахара",                "essential": true,  "important": false },
      { "id": "honey",          "name": "2 ст. л. мёда",               "essential": false, "important": true },
      { "id": "cinnamon",       "name": "1 ст. л. корицы",             "essential": false, "important": true },
      { "id": "flour",          "name": "1,5 стакана муки",            "essential": false, "important": false }
    ],
    "steps": [
      "Подогреть мёд, смешать с сахаром, яйцами и содой",
      "Добавить корицу",
      "Всыпать муку, замесить тесто",
      "Сформировать шарики (смочить руки водой при необходимости)",
      "Выложить на противень с пергаментом",
      "Выпекать 15 минут при 180°C до золотистости",
      "Остудить и подавать"
    ]
  }
]
